breathe/__init__.py
breathe/apidoc.py
breathe/exception.py
breathe/file_state_cache.py
breathe/filetypes.py
breathe/path_handler.py
breathe/process.py
breathe/project.py
breathe/directives/__init__.py
breathe/directives/class_like.py
breathe/directives/content_block.py
breathe/directives/file.py
breathe/directives/function.py
breathe/directives/index.py
breathe/directives/item.py
breathe/directives/setup.py
breathe/finder/__init__.py
breathe/finder/compound.py
breathe/finder/factory.py
breathe/finder/index.py
breathe/parser/__init__.py
breathe/parser/compound.py
breathe/parser/compoundsuper.py
breathe/parser/index.py
breathe/parser/indexsuper.py
breathe/renderer/__init__.py
breathe/renderer/filter.py
breathe/renderer/mask.py
breathe/renderer/sphinxrenderer.py
breathe/renderer/target.py
breathe-4.34.0.dist-info/LICENSE
breathe-4.34.0.dist-info/METADATA
breathe-4.34.0.dist-info/WHEEL
breathe-4.34.0.dist-info/entry_points.txt
breathe-4.34.0.dist-info/top_level.txt
breathe-4.34.0.dist-info/RECORD
